litchi_wp/__init__.py
litchi_wp/__init__.pyi
litchi_wp/action.py
litchi_wp/action.pyi
litchi_wp/altitude.py
litchi_wp/altitude.pyi
litchi_wp/enums.py
litchi_wp/enums.pyi
litchi_wp/gimbal.py
litchi_wp/gimbal.pyi
litchi_wp/photo.py
litchi_wp/photo.pyi
litchi_wp/poi.py
litchi_wp/poi.pyi
litchi_wp/py.typed
litchi_wp/waypoint.py
litchi_wp/waypoint.pyi
litchi_wp-3.0.0.dist-info/LICENSE
litchi_wp-3.0.0.dist-info/METADATA
litchi_wp-3.0.0.dist-info/WHEEL
litchi_wp-3.0.0.dist-info/top_level.txt
litchi_wp-3.0.0.dist-info/RECORD
