Metadata-Version: 2.1
Name: litchi-wp
Version: 3.0.0
Summary: Easy to manage litchi waypoints for csv
License: MIT License
Project-URL: Documentation, https://joekae.github.io/litchi_wp/litchi_wp/waypoint.html
Project-URL: GitHub, https://github.com/JoeKae/litchi-wp
Project-URL: Changelog, https://github.com/JoeKae/litchi_wp/blob/main/CHANGELOG.md
Keywords: litchi,waypoint,drone,dji,csv
Classifier: License :: OSI Approved :: MIT License
Classifier: Programming Language :: Python
Classifier: Programming Language :: Python :: 3
Requires-Python: >=3.10
License-File: LICENSE
Provides-Extra: dev
